Metadata-Version: 2.1
Name: edvsdk
Version: 0.1
Summary: edv sdk
Home-page: UNKNOWN
Author: hj
Author-email: 1599712264@qq.com
License: UNKNOWN
Platform: UNKNOWN
